[
{
    "id":"12345",
    "firstname":"Gaetan",
    "lastname":"Emmanuel",
    "cover":"https://www.gravatar.com/avatar/2c7d99fe281ecd3bcd65ab915bac6dd5?s=250",
    "category":"family",
    "phones":{
        "personnal":"+509 44 26 3331",
        "company":"+509 43 80 8524"
    },
    "email":"gayetan.an@gmail.com"
},
{"id":"12345",
    "firstname":"Gaetan",
    "lastname":"Emmanuel",
    "cover":"https://www.gravatar.com/avatar/2c7d99fe281ecd3bcd65ab915bac6dd5?s=250",
    "category":"family",
    "phones":{
        "personnal":"+509 44 26 3331",
        "company":"+509 43 80 8524"
    },
    "email":"gayetan.an@gmail.com"
}
]